takes/__init__.py
takes/takes.py
takes-0.2.0.dist-info/LICENSE
takes-0.2.0.dist-info/METADATA
takes-0.2.0.dist-info/WHEEL
takes-0.2.0.dist-info/top_level.txt
takes-0.2.0.dist-info/RECORD
