Metadata-Version: 2.1
Name: takes
Version: 0.2.0
Summary: Decorator for run-time type checks.
Home-page: https://github.com/pymetrics/takes
Author: Chris Lawlor
Author-email: chris@pymetrics.com
License: MIT license
Keywords: takes
Platform: UNKNOWN
Classifier: Development Status :: 2 - Pre-Alpha
Classifier: Intended Audience :: Developers
Classifier: License :: OSI Approved :: MIT License
Classifier: Natural Language :: English
Classifier: Programming Language :: Python :: 3
Classifier: Programming Language :: Python :: 3.6
Classifier: Programming Language :: Python :: 3.7
Classifier: Programming Language :: Python :: 3.8
Classifier: Programming Language :: Python :: 3.9
Requires-Python: >=3.6
License-File: LICENSE
